setup.py
that.py
that.egg-info/PKG-INFO
that.egg-info/SOURCES.txt
that.egg-info/dependency_links.txt
that.egg-info/top_level.txt